healthy_django/__init__.py
healthy_django/admin.py
healthy_django/apps.py
healthy_django/conf.py
healthy_django/exceptions.py
healthy_django/models.py
healthy_django/urls.py
healthy_django/views.py
healthy_django/healthcheck/base.py
healthy_django/healthcheck/celery_queue_length.py
healthy_django/healthcheck/django_cache.py
healthy_django/healthcheck/django_database.py
healthy_django/healthcheck/sqs_length.py
healthy_django/static/css/healthy_django.css
healthy_django/static/js/healthy_django.js
healthy_django/templates/base.html
healthy_django/templates/index.html
healthy_django/templates/healthy_django/index.html
healthy_django/test_utils/__init__.py
healthy_django/test_utils/test_app/__init__.py
healthy_django/test_utils/test_app/admin.py
healthy_django/test_utils/test_app/apps.py
healthy_django/test_utils/test_app/models.py
healthy_django/test_utils/test_app/migrations/__init__.py
healthy_django-0.1.0.dist-info/AUTHORS.rst
healthy_django-0.1.0.dist-info/LICENSE
healthy_django-0.1.0.dist-info/METADATA
healthy_django-0.1.0.dist-info/WHEEL
healthy_django-0.1.0.dist-info/top_level.txt
healthy_django-0.1.0.dist-info/RECORD
