Metadata-Version: 2.1
Name: healthy-django
Version: 0.1.0
Summary: Simple Re Usable tool for Django Healthchecks
Home-page: https://github.com/vigneshhari/healthy_django
Author: Vignesh Hari
Author-email: vignesh@securityadvisor.io
License: Apache Software License 2.0
Keywords: healthy_django
Platform: UNKNOWN
Classifier: Development Status :: 3 - Alpha
Classifier: Framework :: Django :: 2.1
Classifier: Intended Audience :: Developers
Classifier: License :: OSI Approved :: BSD License
Classifier: Natural Language :: English
Classifier: Programming Language :: Python :: 2
Classifier: Programming Language :: Python :: 2.7
Classifier: Programming Language :: Python :: 3
Classifier: Programming Language :: Python :: 3.5
Classifier: Programming Language :: Python :: 3.6
License-File: LICENSE
License-File: AUTHORS.rst
Requires-Dist: boto3 (>=1.9.86)
